Memory_elements/jkff.v
//jkff modules represents a JK type flip-flop
module jkff(j,k,clk,q,qn);
	input j,k,clk;
	output q,qn;
	reg q,qn;

	//Initialize flip-flop outputs
	initial begin q=0; qn=1; end

	//Change output on positive clock edge
	always @(posedge clk) 
	begin
		q <= (j&qn)|((!k)&q);
		qn <= (!j|q)&(k|qn);
	end
endmodule


module tester(q,qn,clk,j,k);
	input q,qn;
	output clk,j,k;
	reg clk,j,k;

	//Run the test once
	initial
	begin
		clk=0;
		//Dump results of the simulation to ff.cvd
		$dumpfile("jkff.vcd");
		$dumpvars;
		//Generate input signal j,k
		   j=0;k=0; #9 j=1;k=0; #1 j=0;k=1; #1 j=1;k=1; #2 j=0;k=0; #1 j=1;k=0; #12 j=0;k=1;
		#1 j=1;k=0; #2 j=0;k=0; #1 j=1;k=1; #1 j=0;k=0; #1 j=1;k=1; #1 j=0;k=1; #7 j=1;k=0;
		#8 $finish;
	end

	//Generate periodic clock signal
	always
	begin
		#4 clk=!clk;
	end
endmodule


module testbench;
	wire clk,j,k,q,qn;
	jkff ff1(j,k,clk,q,qn);//creating an instance of the module
	tester tst1(q,qn,clk,j,k);//creating an instance of the module
endmodule

Memory_elements/jkff.vcd
$date
	Sat Nov 22 19:52:02 2014
$end
$version
	Icarus Verilog
$end
$timescale
	1s
$end
$scope module testbench $end
$var wire 1 ! clk $end
$var wire 1 " j $end
$var wire 1 # k $end
$var wire 1 $ q $end
$var wire 1 % qn $end
$scope module ff1 $end
$var wire 1 ! clk $end
$var wire 1 " j $end
$var wire 1 # k $end
$var reg 1 & q $end
$var reg 1 ' qn $end
$upscope $end
$scope module tst1 $end
$var wire 1 $ q $end
$var wire 1 % qn $end
$var reg 1 ( clk $end
$var reg 1 ) j $end
$var reg 1 * k $end
$upscope $end
$upscope $end
$enddefinitions $end
#0
$dumpvars
0*
0)
0(
1'
0&
1%
0$
0#
0"
0!
$end
#4
1(
1!
#8
0(
0!
#9
1)
1"
#10
1*
1#
0)
0"
#11
1)
1"
#12
0'
0%
1&
1$
1(
1!
#13
0*
0#
0)
0"
#14
1)
1"
#16
0(
0!
#20
1(
1!
#24
0(
0!
#26
1*
1#
0)
0"
#27
0*
0#
1)
1"
#28
1(
1!
#29
0)
0"
#30
1*
1#
1)
1"
#31
0*
0#
0)
0"
#32
1*
1#
1)
1"
0(
0!
#33
0)
0"
#36
1'
1%
0&
0$
1(
1!
#40
0(
0!
0*
0#
1)
1"
#44
0'
0%
1&
1$
1(
1!
