Memory_elements/ripplec.v
// This is a mod 16 ripple counter made with a test bench, testing 
// till about 200 seconds. This is made out of composite blocks 
// such as D and T flipflops. If an output is to be given as a parameter
// for another composite system, indicate it as an output only. 
// Otherwise, for the bottom most subsystem, indicate it as a output reg.
// Do the initializing for the subsystem block. 

// This is the BOTTOM UP Procedure.


module ripplec(q,clk,reset);
	input clk,reset;
	output [3:0] q;
	
	
	tff1 tf0(q[0],clk,reset);
	tff1 tf1(q[1],q[0],reset);
	tff1 tf2(q[2],q[1],reset);
	tff1 tf3(q[3],q[2],reset);
endmodule

module tff1(q,clk,reset);
	output q;
	input clk,reset;
	wire d;
	

	dff1 dff0(q,d,clk,reset);
	not n1(d,q);

endmodule

module dff1(q,d,clk,reset);
	input reset,d,clk;
	output reg q;

	initial begin q=0; end
	
	always @(posedge reset or negedge clk)
	begin
	if(reset)
	begin
		q=1'b0;
	end
	
	else 
	begin
		q=d;	
	end	
	end
endmodule

module stimulus;
	reg clk;
	reg reset;
	wire [3:0] q;

	initial 
	begin
		$dumpfile("ripplec.vcd");
		$dumpvars;
	end
		


	//instantiate the main block first, which further contains the sub blocks

	ripplec tst(q,clk,reset);
	//setting the clock reference
	initial
	begin
		clk=1'b0;
	end
	always
	begin
		#5 clk=~clk;
	end

	initial 
	begin
		reset=1'b1;
		#15 reset=1'b0;
		#180 reset=1'b1;
		#10 reset=1'b0;
		#20 $finish;
		//This terminates the simulation
	end

	//For monitoring the outputs
	initial 
	$monitor($time, "Output q=%b%b%b%b", q[3],q[2],q[1],q[0]);

endmodule

Memory_elements/ripplec.vcd
$date
	Mon Dec 01 15:27:29 2014
$end
$version
	Icarus Verilog
$end
$timescale
	1s
$end
$scope module stimulus $end
$var wire 4 ! q [3:0] $end
$var reg 1 " clk $end
$var reg 1 # reset $end
$scope module tst $end
$var wire 1 $ clk $end
$var wire 4 % q [3:0] $end
$var wire 1 & reset $end
$scope module tf0 $end
$var wire 1 $ clk $end
$var wire 1 ' d $end
$var wire 1 ( q $end
$var wire 1 & reset $end
$scope module dff0 $end
$var wire 1 $ clk $end
$var wire 1 ' d $end
$var wire 1 & reset $end
$var reg 1 ) q $end
$upscope $end
$upscope $end
$scope module tf1 $end
$var wire 1 * clk $end
$var wire 1 + d $end
$var wire 1 , q $end
$var wire 1 & reset $end
$scope module dff0 $end
$var wire 1 * clk $end
$var wire 1 + d $end
$var wire 1 & reset $end
$var reg 1 - q $end
$upscope $end
$upscope $end
$scope module tf2 $end
$var wire 1 . clk $end
$var wire 1 / d $end
$var wire 1 0 q $end
$var wire 1 & reset $end
$scope module dff0 $end
$var wire 1 . clk $end
$var wire 1 / d $end
$var wire 1 & reset $end
$var reg 1 1 q $end
$upscope $end
$upscope $end
$scope module tf3 $end
$var wire 1 2 clk $end
$var wire 1 3 d $end
$var wire 1 4 q $end
$var wire 1 & reset $end
$scope module dff0 $end
$var wire 1 2 clk $end
$var wire 1 3 d $end
$var wire 1 & reset $end
$var reg 1 5 q $end
$upscope $end
$upscope $end
$upscope $end
$upscope $end
$enddefinitions $end
#0
$dumpvars
05
04
13
02
01
00
1/
0.
0-
0,
1+
0*
0)
0(
1'
1&
b0 %
0$
1#
0"
b0 !
$end
#5
1"
1$
#10
0"
0$
#15
1"
1$
0#
0&
#20
0'
1*
1)
1(
b1 !
b1 %
0"
0$
#25
1"
1$
#30
0+
1.
1-
1,
1'
0*
0)
0(
b10 !
b10 %
0"
0$
#35
1"
1$
#40
0'
1*
1)
1(
b11 !
b11 %
0"
0$
#45
1"
1$
#50
0/
12
11
10
1+
0.
0-
0,
1'
0*
0)
0(
b100 !
b100 %
0"
0$
#55
1"
1$
#60
0'
1*
1)
1(
b101 !
b101 %
0"
0$
#65
1"
1$
#70
0+
1.
1-
1,
1'
0*
0)
0(
b110 !
b110 %
0"
0$
#75
1"
1$
#80
0'
1*
1)
1(
b111 !
b111 %
0"
0$
#85
1"
1$
#90
03
15
14
1/
02
01
00
1+
0.
0-
0,
1'
0*
0)
0(
b1000 !
b1000 %
0"
0$
#95
1"
1$
#100
0'
1*
1)
1(
b1001 !
b1001 %
0"
0$
#105
1"
1$
#110
0+
1.
1-
1,
1'
0*
0)
0(
b1010 !
b1010 %
0"
0$
#115
1"
1$
#120
0'
1*
1)
1(
b1011 !
b1011 %
0"
0$
#125
1"
1$
#130
0/
12
11
10
1+
0.
0-
0,
1'
0*
0)
0(
b1100 !
b1100 %
0"
0$
#135
1"
1$
#140
0'
1*
1)
1(
b1101 !
b1101 %
0"
0$
#145
1"
1$
#150
0+
1.
1-
1,
1'
0*
0)
0(
b1110 !
b1110 %
0"
0$
#155
1"
1$
#160
0'
1*
1)
1(
b1111 !
b1111 %
0"
0$
#165
1"
1$
#170
13
05
04
1/
02
01
00
1+
0.
0-
0,
1'
0*
0)
0(
b0 !
b0 %
0"
0$
#175
1"
1$
#180
0'
1*
1)
1(
b1 !
b1 %
0"
0$
#185
1"
1$
#190
0+
1.
1-
1,
1'
0*
0)
0(
b10 !
b10 %
0"
0$
#195
1+
0.
0-
0,
b0 !
b0 %
1"
1$
1#
1&
#200
0"
0$
#205
1"
1$
0#
0&
#210
0'
1*
1)
1(
b1 !
b1 %
0"
0$
#215
1"
1$
#220
0+
1.
1-
1,
1'
0*
0)
0(
b10 !
b10 %
0"
0$
