Memory_elements/tff.v
module tff(t,clk,q,qn);
	input t,clk;
	output q,qn;
	reg q,qn;

	initial begin q=0;qn=1; end

	always @(posedge clk)
	begin
		q <= (t^q);
		qn <= (t~^q);
	end
endmodule

module tester(q,qn,clk,t);
	input q,qn;
	output clk,t;
	reg clk,t;

	//Run the test once
	initial
	begin
		clk=0;
		//Dump results of the simulation to ff.cvd
		$dumpfile("tff.vcd");
		$dumpvars;
		//Generate input signal t
		   t=0; #9 t=1; #1 t=0; #1 t=1; #2 t=0; #1 t=1; #12 t=0;
		#1 t=1; #2 t=0; #1 t=1; #1 t=0; #1 t=1; #1 t=0; # 7 t=1;
		#8 $finish;
	end

	//Generate periodic clock signal
	always
	begin
		#4 clk=!clk;
	end
endmodule


module testbench;
	wire clk,t,q,qn;
	tff ff1(t,clk,q,qn);
	tester tst1(q,qn,clk,t);
endmodule

Memory_elements/tff.vcd
$date
	Sun Nov 23 07:06:32 2014
$end
$version
	Icarus Verilog
$end
$timescale
	1s
$end
$scope module testbench $end
$var wire 1 ! clk $end
$var wire 1 " q $end
$var wire 1 # qn $end
$var wire 1 $ t $end
$scope module ff1 $end
$var wire 1 ! clk $end
$var wire 1 $ t $end
$var reg 1 % q $end
$var reg 1 & qn $end
$upscope $end
$scope module tst1 $end
$var wire 1 " q $end
$var wire 1 # qn $end
$var reg 1 ' clk $end
$var reg 1 ( t $end
$upscope $end
$upscope $end
$enddefinitions $end
#0
$dumpvars
0(
0'
1&
0%
0$
1#
0"
0!
$end
#4
1'
1!
#8
0'
0!
#9
1(
1$
#10
0(
0$
#11
1(
1$
#12
0&
0#
1%
1"
1'
1!
#13
0(
0$
#14
1(
1$
#16
0'
0!
#20
1&
1#
0%
0"
1'
1!
#24
0'
0!
#26
0(
0$
#27
1(
1$
#28
0&
0#
1%
1"
1'
1!
#29
0(
0$
#30
1(
1$
#31
0(
0$
#32
1(
1$
0'
0!
#33
0(
0$
#36
1'
1!
#40
0'
0!
1(
1$
#44
1&
1#
0%
0"
1'
1!
