Combi_elements/DMux8.v
module DMux8(in,sel,clk,a,b,c,d,e,f,g,h);
	input in,clk;
	input [2:0] sel;
	output reg a,b,c,d,e,f,g,h;
	reg p1;

	initial begin p1=sel[2]?1:0; end
	always @(posedge(clk))
	begin
	if(sel==3'b000)
	begin
		a=in;
		b=0;c=0;d=0;e=0;f=0;g=0;h=0;
	end
	if(sel==3'b001)
	begin
		a=0;
		b=in;c=0;d=0;e=0;f=0;g=0;h=0;
	end
	if(sel==3'b010)
	begin
		a=0;
		b=0;c=in;d=0;e=0;f=0;g=0;h=0;
	end
	if(sel==3'b011)
	begin
		a=0;
		b=0;c=0;d=in;e=0;f=0;g=0;h=0;
	end
	if(sel==3'b100)
	begin
		a=0;
		b=0;c=0;d=0;e=in;f=0;g=0;h=0;
	end
	if(sel==3'b101)
	begin
		a=0;
		b=0;c=0;d=0;e=0;f=in;g=0;h=0;
	end
	if(sel==3'b110)
	begin
		a=0;
		b=0;c=0;d=0;e=0;f=0;g=in;h=0;
	end
	if(sel==3'b111)
	begin
		a=0;
		b=0;c=0;d=0;e=0;f=0;g=0;h=in;
	end
	end
endmodule

module DMux4(in,sel,clk,a,b,c,d);
	input in,clk;
	input [1:0] sel; 
	//Assuming that sel[1] is the MSB, and sel[0] is the LSB
	output reg a,b,c,d;
	reg p1,p2,p3,p4;
	
	always @(posedge(clk))
	begin
	if(sel==2'b00)
	begin
		a<=in;
		b=0;c=0;d=0;
	end
	if(sel==2'b01)
	begin
		b=in;
		a=0;c=0;d=0;
	end
	if(sel==2'b10)
	begin
		c=in;
		b=0;a=0;d=0;
	end
	if(sel==2'b11)
	begin
		d=in;
		b=0;c=0;a=0;
	end	
	
	end
	
endmodule

module stimulus();
	reg in,clk;
	reg [2:0] sel;
	wire a,b,c,d,e,f,g,h;

	//Instantiate the object
	DMux8 tester(in,sel,clk,a,b,c,d,e,f,g,h);

	initial
	begin
		$dumpfile("DMux8.vcd");
		$dumpvars;
	end

	initial
	begin
		clk=1'b0;
	end
	always
	begin
		#5 clk=~clk;
	end

	initial 
	begin
		
		#10 in=1;sel=3'b000;
		#10 in=1;sel=3'b001;
		#10 in=1;sel=3'b010;
		#10 in=1;sel=3'b011;
		#10 in=1;sel=3'b100;
		#10 in=1;sel=3'b101;
		#10 in=1;sel=3'b110;
		#10 in=1;sel=3'b111;
		#10 $finish;
	end
	

	initial
	begin
		$monitor($time, "sel[2]=%b",sel[2]);
	end

	endmodule

Combi_elements/DMux8.vcd
$date
	Tue Dec 02 21:59:50 2014
$end
$version
	Icarus Verilog
$end
$timescale
	1s
$end
$scope module DMux4 $end
$var wire 1 ! clk $end
$var wire 1 " in $end
$var wire 2 # sel [1:0] $end
$var reg 1 $ a $end
$var reg 1 % b $end
$var reg 1 & c $end
$var reg 1 ' d $end
$upscope $end
$scope module stimulus $end
$var wire 1 ( a $end
$var wire 1 ) b $end
$var wire 1 * c $end
$var wire 1 + d $end
$var wire 1 , e $end
$var wire 1 - f $end
$var wire 1 . g $end
$var wire 1 / h $end
$var reg 1 0 clk $end
$var reg 1 1 in $end
$var reg 3 2 sel [2:0] $end
$scope module tester $end
$var wire 1 3 clk $end
$var wire 1 4 in $end
$var wire 3 5 sel [2:0] $end
$var reg 1 6 a $end
$var reg 1 7 b $end
$var reg 1 8 c $end
$var reg 1 9 d $end
$var reg 1 : e $end
$var reg 1 ; f $end
$var reg 1 < g $end
$var reg 1 = h $end
$var reg 1 > p1 $end
$upscope $end
$upscope $end
$enddefinitions $end
#0
$dumpvars
x>
x=
x<
x;
x:
x9
x8
x7
x6
bx 5
x4
03
bx 2
x1
00
x/
x.
x-
x,
x+
x*
x)
x(
x'
x&
x%
x$
bz #
z"
z!
$end
#5
10
13
#10
00
03
b0 2
b0 5
11
14
#15
0=
0/
0<
0.
0;
0-
0:
0,
09
0+
08
0*
07
0)
16
1(
10
13
#20
00
03
b1 2
b1 5
#25
17
1)
06
0(
10
13
#30
00
03
b10 2
b10 5
#35
18
1*
07
0)
10
13
#40
00
03
b11 2
b11 5
#45
19
1+
08
0*
10
13
#50
00
03
b100 2
b100 5
#55
1:
1,
09
0+
10
13
#60
00
03
b101 2
b101 5
#65
1;
1-
0:
0,
10
13
#70
00
03
b110 2
b110 5
#75
1<
1.
0;
0-
10
13
#80
00
03
b111 2
b111 5
#85
1=
1/
0<
0.
10
13
